[1,["5aK/a7OM1MD7Gg+8Ez7cMk","76K3Ti1zpMGZTL1v3Tgcpr@6c48a"],["node","root","skeleton","data","_skeletonData"],[["cc.Node",["_name","_layer","_children","_components","_prefab","_parent"],1,2,9,4,1],["cc.UITransform",["node","__prefab","_contentSize","_anchorPoint"],3,1,4,5,5],["cc.Prefab",["_name"],2],["cc.Node",["_name","_layer","_parent","_components","_prefab"],1,1,12,4],["cc.CompPrefabInfo",["fileId"],2],["01a6b9cIhxLZZJGmuYVfRUv",["animation","hits","damage","node","__prefab","skeleton"],0,1,4,1],["cc.PrefabInfo",["fileId","instance","targetOverrides","nestedPrefabInstanceRoots","root","asset"],-1,1,1],["sp.Skeleton",["defaultSkin","defaultAnimation","_premultipliedAlpha","_preCacheMode","node","__prefab"],-1,1,4],["sp.SkeletonData",["_name","_atlasText","textureNames","_skeletonJson","textures"],-1,3]],[[4,0,2],[6,0,1,2,3,4,5,5],[1,0,1,1],[2,0,2],[0,0,1,2,3,4,3],[0,0,1,5,2,3,4,3],[3,0,1,2,3,4,3],[1,0,1,2,3,1],[5,0,1,2,3,4,5,4],[7,0,1,2,3,4,5,5],[8,0,1,2,3,4,5]],[[[[3,"2005_projectile_hit"],[4,"2005_projectile_hit",33554432,[-5],[[2,-2,[0,"3eZj06FVNPNJZOlVmYUr7h"]],[8,"impact",0,1,-4,[0,"1a2w8wINdK6ppmB6OZN9qy"],-3]],[1,"307kAO7K1GGosnzdcHJKuj",null,null,null,-1,0]],[5,"Pivot",33554432,1,[-7],[[2,-6,[0,"50zTK/rABBTZSaENmrO2i3"]]],[1,"0c4GiMvphKMpJMFI+t5xsl",null,null,null,1,0]],[6,"Skeleton",33554432,2,[[[7,-8,[0,"a0BE6WXu1GRacCHc69s9L+"],[5,114.0999984741211,132.0500030517578],[0,0.5702892249344129,0.4546005103518835]],-9],4,1],[1,"96r3IN4kZGSbprk404lQeg",null,null,null,1,0]],[9,"default","impact",false,0,3,[0,"14kYnEnOND+bp0jxTPfTS5"]]],0,[0,1,1,0,0,1,0,2,4,0,0,1,0,-1,2,0,0,2,0,-1,3,0,0,3,0,-2,4,0,3,1,9],[4],[4],[0]],[[[10,"hero_05_fx","\nhero_05_fx.png\nsize: 512,512\nformat: RGBA8888\nfilter: Linear,Linear\nrepeat: none\nfx_bullet\n  rotate: false\n  xy: 171, 24\n  size: 79, 31\n  orig: 79, 31\n  offset: 0, 0\n  index: -1\nfx_folk\n  rotate: false\n  xy: 2, 179\n  size: 136, 318\n  orig: 136, 318\n  offset: 0, 0\n  index: -1\nfx_tentacle\n  rotate: true\n  xy: 140, 179\n  size: 238, 141\n  orig: 238, 141\n  offset: 0, 0\n  index: -1\nhit\n  rotate: false\n  xy: 2, 74\n  size: 105, 103\n  orig: 108, 107\n  offset: 2, 2\n  index: -1\nhit/0\n  rotate: false\n  xy: 264, 421\n  size: 53, 28\n  orig: 64, 64\n  offset: 6, 18\n  index: -1\nhit/1\n  rotate: false\n  xy: 283, 257\n  size: 35, 30\n  orig: 64, 64\n  offset: 26, 17\n  index: -1\nhit/2\n  rotate: false\n  xy: 283, 388\n  size: 23, 31\n  orig: 64, 64\n  offset: 38, 15\n  index: -1\nimpact/0\n  rotate: false\n  xy: 283, 289\n  size: 28, 28\n  orig: 64, 64\n  offset: 17, 19\n  index: -1\nimpact/1\n  rotate: false\n  xy: 283, 222\n  size: 33, 33\n  orig: 64, 64\n  offset: 15, 16\n  index: -1\nimpact/10\n  rotate: false\n  xy: 109, 58\n  size: 57, 57\n  orig: 64, 64\n  offset: 3, 3\n  index: -1\nimpact/11\n  rotate: false\n  xy: 203, 419\n  size: 59, 59\n  orig: 64, 64\n  offset: 3, 2\n  index: -1\nimpact/12\n  rotate: false\n  xy: 173, 116\n  size: 60, 61\n  orig: 64, 64\n  offset: 2, 1\n  index: -1\nimpact/13\n  rotate: false\n  xy: 109, 117\n  size: 62, 60\n  orig: 64, 64\n  offset: 2, 1\n  index: -1\nimpact/14\n  rotate: false\n  xy: 140, 419\n  size: 61, 58\n  orig: 64, 64\n  offset: 2, 1\n  index: -1\nimpact/15\n  rotate: true\n  xy: 235, 115\n  size: 62, 56\n  orig: 64, 64\n  offset: 2, 2\n  index: -1\nimpact/2\n  rotate: true\n  xy: 283, 179\n  size: 41, 39\n  orig: 64, 64\n  offset: 11, 14\n  index: -1\nimpact/3\n  rotate: false\n  xy: 264, 451\n  size: 46, 46\n  orig: 64, 64\n  offset: 8, 10\n  index: -1\nimpact/4\n  rotate: false\n  xy: 252, 6\n  size: 48, 49\n  orig: 64, 64\n  offset: 7, 7\n  index: -1\nimpact/5\n  rotate: false\n  xy: 116, 3\n  size: 53, 53\n  orig: 64, 64\n  offset: 5, 4\n  index: -1\nimpact/6\n  rotate: false\n  xy: 60, 2\n  size: 54, 54\n  orig: 64, 64\n  offset: 5, 4\n  index: -1\nimpact/7\n  rotate: false\n  xy: 2, 17\n  size: 56, 55\n  orig: 64, 64\n  offset: 4, 3\n  index: -1\nimpact/8\n  rotate: false\n  xy: 168, 58\n  size: 56, 56\n  orig: 64, 64\n  offset: 4, 3\n  index: -1\nimpact/9\n  rotate: false\n  xy: 226, 57\n  size: 56, 56\n  orig: 64, 64\n  offset: 4, 3\n  index: -1\n",["hero_05_fx.png"],{"skeleton":{"hash":"6JO3PwqbJDg1T0gaaq+05G53St8","spine":"3.8.99","x":-65.07,"y":-60.03,"width":114.1,"height":132.05,"images":"./image/","audio":"D:/_Projects/Main/Sushi/Hero/Hero2/FX"},"bones":[{"name":"root"},{"name":"scale","parent":"root","scaleX":0.25,"scaleY":0.25},{"name":"enemy","parent":"scale","scaleX":1.2,"scaleY":1.2},{"name":"bullet","parent":"scale","scaleX":1.3977,"scaleY":1.3977},{"name":"impact","parent":"scale"},{"name":"tentacle","parent":"scale","y":7.55,"color":"ffc300ff"},{"name":"folk","parent":"scale","length":205.29,"rotation":90,"x":3.94,"y":65.5,"color":"ffc300ff"},{"name":"hit_fx","parent":"scale","y":105.28,"color":"ff5300ff"},{"name":"hit2_1","parent":"scale","scaleX":2.9394,"scaleY":2.9394,"color":"8dff00ff"},{"name":"hit2_2","parent":"scale","rotation":177.77,"scaleX":2.9394,"scaleY":2.9394,"color":"8dff00ff"}],"slots":[{"name":"enemy1","bone":"enemy","dark":"000000"},{"name":"fx_bullet","bone":"bullet"},{"name":"impact","bone":"impact"},{"name":"hit","bone":"hit_fx"},{"name":"fx_tentacle","bone":"tentacle"},{"name":"fx_tentacle_overlay","bone":"tentacle","blend":"additive"},{"name":"fx_folk","bone":"folk"},{"name":"fx_folk_overlay","bone":"folk","blend":"additive"},{"name":"hit2","bone":"hit2_1"},{"name":"hit3","bone":"hit2_2"}],"skins":[{"name":"default","attachments":{"fx_bullet":{"fx_bullet":{"y":0.5,"width":314,"height":125}},"fx_folk":{"fx_folk":{"x":621.5,"y":-0.5,"rotation":-90,"width":545,"height":1270}},"fx_folk_overlay":{"fx_folk":{"x":621.5,"y":-0.5,"rotation":-90,"width":545,"height":1270}},"fx_tentacle":{"fx_tentacle":{"x":0.5,"y":0.5,"width":953,"height":565}},"fx_tentacle_overlay":{"fx_tentacle":{"x":0.5,"y":0.5,"width":953,"height":565}},"hit":{"hit":{"x":0.5,"y":0.5,"width":431,"height":427}},"hit2":{"hit/0":{"width":256,"height":256},"hit/1":{"width":256,"height":256},"hit/2":{"width":256,"height":256}},"hit3":{"hit/0":{"width":256,"height":256},"hit/1":{"width":256,"height":256},"hit/2":{"width":256,"height":256}},"impact":{"impact/0":{"width":256,"height":256},"impact/1":{"width":256,"height":256},"impact/2":{"width":256,"height":256},"impact/3":{"width":256,"height":256},"impact/4":{"width":256,"height":256},"impact/5":{"width":256,"height":256},"impact/6":{"width":256,"height":256},"impact/7":{"width":256,"height":256},"impact/8":{"width":256,"height":256},"impact/9":{"width":256,"height":256},"impact/10":{"width":256,"height":256},"impact/11":{"width":256,"height":256},"impact/12":{"width":256,"height":256},"impact/13":{"width":256,"height":256},"impact/14":{"width":256,"height":256},"impact/15":{"width":256,"height":256}}}}],"events":{"hit":{}},"animations":{"bullet":{"slots":{"fx_bullet":{"attachment":[{"name":"fx_bullet"}]}},"bones":{"bullet":{"scale":[{},{"time":0.1,"x":0.862,"y":1.169},{"time":0.2}]}}},"impact":{"slots":{"impact":{"attachment":[{"name":"impact/0"},{"time":0.0333,"name":"impact/1"},{"time":0.0667,"name":"impact/2"},{"time":0.1,"name":"impact/3"},{"time":0.1333,"name":"impact/4"},{"time":0.1667,"name":"impact/5"},{"time":0.2,"name":"impact/6"},{"time":0.2333,"name":"impact/7"},{"time":0.2667,"name":"impact/8"},{"time":0.3,"name":"impact/9"},{"time":0.3333,"name":"impact/10"},{"time":0.3667,"name":"impact/11"},{"time":0.4,"name":"impact/12"},{"time":0.4333,"name":"impact/13"},{"time":0.4667,"name":"impact/14"},{"time":0.5,"name":"impact/15"},{"time":0.5333,"name":null},{"time":0.5667,"name":"impact/0"}]}},"bones":{"impact":{"translate":[{"time":0.1333,"curve":0.25,"c4":0.57},{"time":0.5,"y":-110.33,"curve":"stepped"},{"time":0.5667}],"scale":[{"x":2.744,"y":2.744}]}}},"impact_skill":{"slots":{"fx_folk":{"color":[{"color":"ffffff00","curve":"stepped"},{"time":0.4667,"color":"ffffff00"},{"time":0.5333,"color":"ffffffff"}],"attachment":[{"name":"fx_folk"},{"time":0.7333,"name":null}]},"fx_folk_overlay":{"color":[{"color":"ffffffff"},{"time":0.5667,"color":"ffffff00","curve":"stepped"},{"time":0.6333,"color":"ffffff00","curve":0.253,"c2":0.57,"c3":0.787},{"time":0.7333,"color":"ffffffff"}],"attachment":[{"time":0.5667,"name":"fx_folk"},{"time":0.7333,"name":null}]},"fx_tentacle":{"color":[{"color":"ffffff00"},{"time":0.0667,"color":"ffffffff"}],"attachment":[{"name":"fx_tentacle"},{"time":0.7333,"name":null}]},"fx_tentacle_overlay":{"color":[{"color":"ffffff00"},{"time":0.0667,"color":"ffffffff"},{"time":0.5667,"color":"ffffff00","curve":"stepped"},{"time":0.6333,"color":"ffffff00","curve":0.253,"c2":0.57,"c3":0.787},{"time":0.7333,"color":"ffffffff"}],"attachment":[{"time":0.5667,"name":"fx_tentacle"},{"time":0.7333,"name":null}]},"hit":{"color":[{"time":0.2333,"color":"ffffffff"},{"time":0.3333,"color":"ffffff00"},{"time":0.5667,"color":"ffffffff","curve":"stepped"},{"time":0.6333,"color":"ffffffff"},{"time":0.6667,"color":"ffffff00"},{"time":0.7333,"color":"ffffffff","curve":"stepped"},{"time":0.8,"color":"ffffffff"},{"time":0.8667,"color":"ffffff00"}],"attachment":[{"time":0.2,"name":"hit"},{"time":0.3333,"name":null},{"time":0.5667,"name":"hit"},{"time":0.6667,"name":null},{"time":0.7333,"name":"hit"},{"time":0.8667,"name":null}]},"hit2":{"attachment":[{"time":0.2,"name":"hit/0"},{"time":0.2667,"name":"hit/1"},{"time":0.3333,"name":"hit/2"},{"time":0.4,"name":null},{"time":0.7333,"name":"hit/0"},{"time":0.8,"name":"hit/1"},{"time":0.8667,"name":"hit/2"},{"time":0.9333,"name":null}]},"hit3":{"attachment":[{"time":0.2333,"name":"hit/0"},{"time":0.3,"name":"hit/1"},{"time":0.3667,"name":"hit/2"},{"time":0.4333,"name":null},{"time":0.7667,"name":"hit/0"},{"time":0.8333,"name":"hit/1"},{"time":0.9,"name":"hit/2"},{"time":0.9667,"name":null}]}},"bones":{"tentacle":{"rotate":[{"angle":39.29},{"time":0.1333,"angle":11.79},{"time":0.2333,"angle":-14.37},{"time":0.3667,"angle":6.23},{"time":0.5333}],"translate":[{"x":-583.44,"y":2143.19,"curve":0,"c2":0.41,"c3":0.75},{"time":0.2,"y":150.73}],"scale":[{"x":0.626,"y":1.524,"curve":0.25,"c4":0.38},{"time":0.2,"x":1.2,"y":0.8},{"time":0.3,"x":0.9,"y":1.1},{"time":0.3667,"x":1.05,"y":0.95},{"time":0.5333},{"time":0.5667,"x":1.2,"y":0.8,"curve":0,"c2":0.55,"c3":0.75},{"time":0.7333,"x":1.5,"y":1.5}]},"folk":{"rotate":[{},{"time":0.4667,"angle":13.53,"curve":"stepped"},{"time":0.5667,"angle":13.53},{"time":0.6667,"angle":1.87}],"translate":[{},{"time":0.4667,"x":-528.23,"y":1471.8,"curve":0,"c2":0.41,"c3":0.75},{"time":0.5667,"y":150.73}],"scale":[{},{"time":0.4667,"x":0.963,"y":0.476},{"time":0.5667,"x":0.8,"y":1.2},{"time":0.6667,"x":1.386,"y":1.386}]},"hit_fx":{"rotate":[{"time":0.2,"curve":"stepped"},{"time":0.5667,"angle":93.7,"curve":"stepped"},{"time":0.7333,"angle":37.45}],"scale":[{},{"time":0.2,"x":3,"y":3},{"time":0.3333,"x":4,"y":4},{"time":0.5667,"x":3,"y":3},{"time":0.6667,"x":4,"y":4,"curve":"stepped"},{"time":0.7333,"x":4,"y":4},{"time":0.8667,"x":6,"y":6}]},"hit2_1":{"rotate":[{},{"time":0.2,"angle":-19.28,"curve":"stepped"},{"time":0.7333,"angle":17.07}],"translate":[{},{"time":0.2,"x":727.94,"y":53.6,"curve":"stepped"},{"time":0.7333,"x":955.48,"y":318.49}],"scale":[{"time":0.2,"curve":"stepped"},{"time":0.7333,"x":2.198,"y":2.198}]},"hit2_2":{"rotate":[{},{"time":0.2333,"angle":27.98,"curve":"stepped"},{"time":0.7667,"angle":-24.11}],"translate":[{},{"time":0.2333,"x":-712.65,"y":21.88,"curve":"stepped"},{"time":0.7667,"x":-807.73,"y":555.05}],"scale":[{},{"time":0.2333,"x":1.233,"y":1.233,"curve":"stepped"},{"time":0.7667,"x":2.038,"y":2.038,"curve":"stepped"},{"time":1.0333,"x":2.038,"y":2.038}]}},"events":[{"time":0.2,"name":"hit"},{"time":0.5667,"name":"hit"},{"time":0.7333,"name":"hit"}]}}},[0]]],0,0,[0],[-1],[1]]]]
